AUTHORS.rst
CONTRIBUTING.rst
HISTORY.rst
LICENSE
MANIFEST.in
README.rst
setup.cfg
setup.py
docs/Makefile
docs/authors.rst
docs/conf.py
docs/contributing.rst
docs/history.rst
docs/index.rst
docs/installation.rst
docs/make.bat
docs/readme.rst
docs/usage.rst
docs/_build/html/_static/file.png
docs/_build/html/_static/minus.png
docs/_build/html/_static/plus.png
eventsourcer/__init__.py
eventsourcer/event.py
eventsourcer.egg-info/PKG-INFO
eventsourcer.egg-info/SOURCES.txt
eventsourcer.egg-info/dependency_links.txt
eventsourcer.egg-info/top_level.txt
eventsourcer/cli/__init__.py
tests/__init__.py
tests/eventsourcer/__init__.py
tests/eventsourcer/test_event.py