Metadata-Version: 2.1
Name: eventsourcer
Version: 0.1.1
Summary: Python Eventsourcing
Home-page: https://github.com/ivangeorgiev/eventsourcer
Author: Ivan Georgiev
Author-email: ivan.georgiev@gmail.com
License: GNU General Public License v3
Keywords: event sourcing
Classifier: Development Status :: 2 - Pre-Alpha
Classifier: License :: OSI Approved :: GNU General Public License v3 (GPLv3)
Classifier: Natural Language :: English
Classifier: Programming Language :: Python :: 3
Classifier: Programming Language :: Python :: 3.7
Classifier: Programming Language :: Python :: 3.8
Classifier: Programming Language :: Python :: 3.9
Classifier: Programming Language :: Python :: 3.10
Classifier: Programming Language :: Python :: 3.11
License-File: LICENSE
License-File: AUTHORS.rst
